integrals_test.pypy310-pp73-x86_64-linux-gnu.so
boringcalculator/__init__.pypy310-pp73-x86_64-linux-gnu.so
boringcalculator/core/processing.pypy310-pp73-x86_64-linux-gnu.so
boringcalculator/core/__init__.pypy310-pp73-x86_64-linux-gnu.so
boringcalculator/tools/__init__.pypy310-pp73-x86_64-linux-gnu.so
boringcalculator/tools/duplicates.pypy310-pp73-x86_64-linux-gnu.so
boringcalculator/parsing/__init__.pypy310-pp73-x86_64-linux-gnu.so
boringcalculator/commands/__init__.pypy310-pp73-x86_64-linux-gnu.so
boringcalculator/commands/__main__.pypy310-pp73-x86_64-linux-gnu.so
boringcalculator-1.0.dist-info/entry_points.txt
boringcalculator-1.0.dist-info/METADATA
boringcalculator-1.0.dist-info/top_level.txt
boringcalculator-1.0.dist-info/WHEEL
boringcalculator-1.0.dist-info/RECORD
